arabic_animations/__init__.py
arabic_animations/cli.py
arabic_animations/main.py
arabic_animations/core/__init__.py
arabic_animations/core/animation.py
arabic_animations/core/color.py
arabic_animations/core/position.py
arabic_animations/core/scene.py
arabic_animations/core/text.py
arabic_animations/utils/__init__.py
arabic_animations/utils/preview.py
arabic_text_animator-0.3.3.dist-info/LICENSE
arabic_text_animator-0.3.3.dist-info/METADATA
arabic_text_animator-0.3.3.dist-info/WHEEL
arabic_text_animator-0.3.3.dist-info/entry_points.txt
arabic_text_animator-0.3.3.dist-info/top_level.txt
arabic_text_animator-0.3.3.dist-info/RECORD
