Metadata-Version: 2.2
Name: arabic-text-animator
Version: 0.3.3
Summary: A Python library for creating Arabic text writing animations
Home-page: https://github.com/saqib-ahmed/arabic-text-animator
Author: Saqib Ahmed
Author-email: saqibahmed515@gmail.com
Classifier: Development Status :: 3 - Alpha
Classifier: Intended Audience :: Developers
Classifier: License :: OSI Approved :: MIT License
Classifier: Programming Language :: Python :: 3
Classifier: Programming Language :: Python :: 3.8
Classifier: Programming Language :: Python :: 3.9
Classifier: Programming Language :: Python :: 3.10
Classifier: Programming Language :: Python :: 3.11
Classifier: Programming Language :: Python :: 3.12
Classifier: Programming Language :: Python :: 3.13
Classifier: Topic :: Software Development :: Libraries :: Python Modules
License-File: LICENSE
Requires-Dist: pycairo>=1.23.0
Requires-Dist: PyGObject>=3.44.1
Requires-Dist: numpy>=1.24.0
Requires-Dist: opencv-python>=4.8.0
Requires-Dist: click>=8.1.7
Requires-Dist: PyQt5>=5.15.0
Requires-Dist: mkdocs>=1.5.0
Requires-Dist: mkdocs-material>=9.0.0
Requires-Dist: mkdocstrings>=0.24.0
Requires-Dist: mkdocstrings-python>=1.7.0
Provides-Extra: docs
Requires-Dist: mkdocs>=1.5.0; extra == "docs"
Requires-Dist: mkdocs-material>=9.0.0; extra == "docs"
Requires-Dist: mkdocstrings>=0.24.0; extra == "docs"
Requires-Dist: mkdocstrings-python>=1.7.0; extra == "docs"
Requires-Dist: mike>=1.1.2; extra == "docs"
Dynamic: author
Dynamic: author-email
Dynamic: classifier
Dynamic: description
Dynamic: description-content-type
Dynamic: home-page
Dynamic: provides-extra
Dynamic: requires-dist
Dynamic: summary
